jupyterlab_s3_browser/__init__.py
jupyterlab_s3_browser/_version.py
jupyterlab_s3_browser/handlers.py
jupyterlab_s3_browser/labextension/package.json
jupyterlab_s3_browser/labextension/static/273.9618d7fe401b1f545801.js
jupyterlab_s3_browser/labextension/static/742.7e7626132f0186fc45d2.js
jupyterlab_s3_browser/labextension/static/747.b58483aab6920bdb0f24.js
jupyterlab_s3_browser/labextension/static/remoteEntry.455474ac5870634af09d.js
jupyterlab_s3_browser/labextension/static/style.js
jupyterlab_s3_browser/labextension/static/third-party-licenses.json
jupyterlab_s3_browser/tests/__init__.py
jupyterlab_s3_browser/tests/test_auth.py
jupyterlab_s3_browser/tests/test_get_s3.py
jupyterlab_s3_browser-0.12.0.data/data/etc/jupyter/jupyter_notebook_config.d/jupyterlab_s3_browser.json
jupyterlab_s3_browser-0.12.0.data/data/etc/jupyter/jupyter_server_config.d/jupyterlab_s3_browser.json
jupyterlab_s3_browser-0.12.0.data/data/share/jupyter/labextensions/jupyterlab-s3-browser/install.json
jupyterlab_s3_browser-0.12.0.data/data/share/jupyter/labextensions/jupyterlab-s3-browser/package.json
jupyterlab_s3_browser-0.12.0.data/data/share/jupyter/labextensions/jupyterlab-s3-browser/static/273.9618d7fe401b1f545801.js
jupyterlab_s3_browser-0.12.0.data/data/share/jupyter/labextensions/jupyterlab-s3-browser/static/742.7e7626132f0186fc45d2.js
jupyterlab_s3_browser-0.12.0.data/data/share/jupyter/labextensions/jupyterlab-s3-browser/static/747.b58483aab6920bdb0f24.js
jupyterlab_s3_browser-0.12.0.data/data/share/jupyter/labextensions/jupyterlab-s3-browser/static/remoteEntry.455474ac5870634af09d.js
jupyterlab_s3_browser-0.12.0.data/data/share/jupyter/labextensions/jupyterlab-s3-browser/static/style.js
jupyterlab_s3_browser-0.12.0.data/data/share/jupyter/labextensions/jupyterlab-s3-browser/static/third-party-licenses.json
jupyterlab_s3_browser-0.12.0.dist-info/LICENSE
jupyterlab_s3_browser-0.12.0.dist-info/METADATA
jupyterlab_s3_browser-0.12.0.dist-info/WHEEL
jupyterlab_s3_browser-0.12.0.dist-info/top_level.txt
jupyterlab_s3_browser-0.12.0.dist-info/RECORD
